wefram/__init__.py
wefram/app.py
wefram/apps.py
wefram/asgi.py
wefram/config.py
wefram/confskel.py
wefram/defaults.py
wefram/exceptions.py
wefram/features.py
wefram/logger.py
wefram/manifest.json
wefram/middlewares.py
wefram/run.py
wefram/runtime.py
wefram/setup.py
wefram/setups.py
wefram/tools.py
wefram/urls.py
wefram/aaa/__init__.py
wefram/aaa/permissions.py
wefram/aaa/routines.py
wefram/aaa/tools.py
wefram/aaa/wrappers.py
wefram/aaa/auth/__init__.py
wefram/aaa/auth/ad.py
wefram/aaa/auth/local.py
wefram/api/__init__.py
wefram/api/base.py
wefram/api/entities.py
wefram/api/mixins.py
wefram/api/models.py
wefram/api/storage.py
wefram/assets/css/02.modals.css
wefram/assets/css/05.system.css
wefram/assets/css/09.dialogs.css
wefram/assets/dist/authorization.jpg
wefram/assets/dist/image-upload.svg
wefram/assets/dist/image.svg
wefram/assets/dist/demo/avatars/avatar1-10.jpg
wefram/assets/dist/demo/avatars/avatar1-11.jpg
wefram/assets/dist/demo/avatars/avatar1-9.jpg
wefram/assets/dist/demo/avatars/avatar10-4.jpg
wefram/assets/dist/demo/avatars/avatar101-4.jpg
wefram/assets/dist/demo/avatars/avatar102-1.jpg
wefram/assets/dist/demo/avatars/avatar102-2.jpg
wefram/assets/dist/demo/avatars/avatar104-4.jpg
wefram/assets/dist/demo/avatars/avatar105-2.jpg
wefram/assets/dist/demo/avatars/avatar107-3.jpg
wefram/assets/dist/demo/avatars/avatar108-4.jpg
wefram/assets/dist/demo/avatars/avatar11-6.jpg
wefram/assets/dist/demo/avatars/avatar111-4.jpg
wefram/assets/dist/demo/avatars/avatar112-4.jpg
wefram/assets/dist/demo/avatars/avatar113-4.jpg
wefram/assets/dist/demo/avatars/avatar114-4.jpg
wefram/assets/dist/demo/avatars/avatar115-4.jpg
wefram/assets/dist/demo/avatars/avatar116-4.jpg
wefram/assets/dist/demo/avatars/avatar117-2.jpg
wefram/assets/dist/demo/avatars/avatar117-4.jpg
wefram/assets/dist/demo/avatars/avatar118-4.jpg
wefram/assets/dist/demo/avatars/avatar119-4.jpg
wefram/assets/dist/demo/avatars/avatar12-4.jpg
wefram/assets/dist/demo/avatars/avatar120-4.jpg
wefram-0.2.54.post4.dist-info/METADATA
wefram-0.2.54.post4.dist-info/WHEEL
wefram-0.2.54.post4.dist-info/entry_points.txt
wefram-0.2.54.post4.dist-info/top_level.txt
wefram-0.2.54.post4.dist-info/RECORD
