Metadata-Version: 2.1
Name: wefram
Version: 0.2.54.post4
Summary: Wefram web platform
Home-page: https://github.com/nf-it/wefram
Author: Denis Khodus
Author-email: deniskhodus@gmail.com
License: UNKNOWN
Platform: UNKNOWN
Classifier: Development Status :: 3 - Alpha
Classifier: Programming Language :: Python :: 3
Classifier: Programming Language :: JavaScript
Classifier: License :: OSI Approved :: MIT License
Classifier: Operating System :: Unix
Classifier: Environment :: Web Environment
Classifier: Framework :: FastAPI
Requires-Python: >=3.9
Requires-Dist: aiofiles
Requires-Dist: aioredis (~=2.0)
Requires-Dist: aiohttp
Requires-Dist: asyncpg
Requires-Dist: greenlet
Requires-Dist: itsdangerous
Requires-Dist: pillow
Requires-Dist: PyJWT
Requires-Dist: pytz
Requires-Dist: SQLAlchemy (~=1.4)
Requires-Dist: starlette
Requires-Dist: starlette-context
Requires-Dist: uvicorn
Requires-Dist: uvloop
Requires-Dist: websockets
Requires-Dist: python-multipart
Requires-Dist: babel
Requires-Dist: jinja2
Requires-Dist: csscompressor
Requires-Dist: jsmin
Requires-Dist: ldap3
Requires-Dist: aiosmtplib
